domainadaptation/__init__.py
domainadaptation-0.0.1.dist-info/METADATA
domainadaptation-0.0.1.dist-info/RECORD
domainadaptation-0.0.1.dist-info/WHEEL
domainadaptation-0.0.1.dist-info/top_level.txt
