Metadata-Version: 2.1
Name: domainadaptation
Version: 0.0.1
Summary: Domain Adaptation Tools for Python
Home-page: http://domainadaptation.org
Author: Steffen Schneider
Author-email: steffen.schneider@tum.de
License: UNKNOWN
Platform: UNKNOWN
Classifier: Programming Language :: Python :: 3
Classifier: License :: OSI Approved :: Mozilla Public License 2.0 (MPL 2.0)
Classifier: Operating System :: OS Independent
Classifier: Development Status :: 1 - Planning
Classifier: Topic :: Scientific/Engineering :: Artificial Intelligence
